americansouth/__init__.py
americansouth/billing_cycle.py
americansouth/cli.py
americansouth/constants.py
americansouth/data_processor.py
americansouth/display.py
americansouth/formatter.py
americansouth/repository.py
americansouth/usage_calculator.py
americansouth-0.2.3.dist-info/METADATA
americansouth-0.2.3.dist-info/WHEEL
americansouth-0.2.3.dist-info/entry_points.txt
americansouth-0.2.3.dist-info/RECORD
