Metadata-Version: 2.3
Name: americansouth
Version: 0.2.3
Summary: Monitor internet data usage to avoid overage charges
Project-URL: Homepage, https://github.com/gkwa/americansouth
Project-URL: Repository, https://github.com/gkwa/americansouth
Author-email: Taylor Monacelli <taylormonacelli@gmail.com>
Requires-Python: >=3.9
Requires-Dist: tzdata>=2024.1
